modelstar/__init__.py
modelstar/builtins/__init__.py
modelstar/builtins/functions/__init__.py
modelstar/builtins/packages/__init__.py
modelstar/builtins/packages/pycaret.zip
modelstar/builtins/procedures/__init__.py
modelstar/builtins/procedures/binary_classifier.py
modelstar/builtins/procedures/classifier.py
modelstar/builtins/procedures/regressor.py
modelstar/builtins/procedures/univariate_time_series_forecast.py
modelstar/cli.py
modelstar/commands/__init__.py
modelstar/commands/create.py
modelstar/commands/database.py
modelstar/commands/download.py
modelstar/commands/project.py
modelstar/commands/register.py
modelstar/commands/run.py
modelstar/commands/upload.py
modelstar/connectors/__init__.py
modelstar/connectors/snowflake/__init__.py
modelstar/connectors/snowflake/context.py
modelstar/connectors/snowflake/context_types.py
modelstar/connectors/snowflake/modelstar/__init__.py
modelstar/connectors/snowflake/sql_dialect/__init__.py
modelstar/connectors/snowflake/sql_dialect/register_sproc.py
modelstar/connectors/snowflake/sql_dialect/register_udf.py
modelstar/connectors/snowflake/utils.py
modelstar/executors/__init__.py
modelstar/executors/config.py
modelstar/executors/project.py
modelstar/executors/py_parser/__init__.py
modelstar/executors/py_parser/implib_snowflake.py
modelstar/executors/py_parser/implib_stdlib.py
modelstar/executors/py_parser/module_call.py
modelstar/executors/py_parser/module_function.py
modelstar/executors/py_parser/module_import.py
modelstar/executors/py_parser/node_visitor.py
modelstar/executors/py_parser/parse_exceptions.py
modelstar/executors/report.py
modelstar/executors/session.py
modelstar/executors/table.py
modelstar/templates/__init__.py
modelstar/templates/report/__init__.py
modelstar/templates/report/base.html
modelstar/templates/report/includes/custom.styles.css
modelstar/templates/report/includes/main.styles.css
modelstar/templates/report/includes/normalize.styles.css
modelstar/templates/report/includes/simple-grid.css
modelstar-0.5.0.dist-info/LICENSE
modelstar-0.5.0.dist-info/METADATA
modelstar-0.5.0.dist-info/WHEEL
modelstar-0.5.0.dist-info/entry_points.txt
modelstar-0.5.0.dist-info/RECORD
