Metadata-Version: 2.1
Name: modelstar
Version: 0.5.0
Summary: DevOps for User Defined Functions and Stored Procedures in Data Warehouses
Home-page: https://modelstar.io
License: Apache-2.0
Keywords: snowflake,forecast,UDF,Stored Procedure
Author: Adithya Krishnan
Author-email: krishsandeep@gmail.com
Requires-Python: >=3.8,<4.0
Classifier: License :: OSI Approved :: Apache Software License
Classifier: Programming Language :: Python :: 3
Classifier: Programming Language :: Python :: 3.8
Classifier: Programming Language :: Python :: 3.9
Classifier: Programming Language :: Python :: 3.10
Classifier: Programming Language :: Python :: 3.11
Requires-Dist: Jinja2 (>=3.1.2,<4.0.0)
Requires-Dist: PyYAML (>=6.0,<7.0)
Requires-Dist: click (>=8.1.3,<9.0.0)
Requires-Dist: joblib (>=1.2.0,<2.0.0)
Requires-Dist: jsonschema (>=4.16.0,<5.0.0)
Requires-Dist: markdown (>=3.4.1,<4.0.0)
Requires-Dist: pandas (>=1.5.1,<2.0.0)
Requires-Dist: snowflake-connector-python (>=2.7.12,<3.0.0)
Requires-Dist: tabulate (>=0.8.10,<0.9.0)
Project-URL: Repository, https://github.com/modelstar-labs
